[
  {
    "id": 1,
    "phone": "+7 977-777-77-77",
    "userId": "uuid",
    "addressId": null,
    "orderPizzas": [
      {
        "id": 1,
        "name": "new",
        "quantity": 2,
        "sauceId": 1,
        "doughId": 1,
        "sizeId": 2,
        "orderId": 1,
        "ingredients": [
          {
            "id": 1,
            "quantity": 2,
            "pizzaId": 1,
            "ingredientId": 3
          },
          {
            "id": 2,
            "quantity": 1,
            "pizzaId": 1,
            "ingredientId": 4
          }
        ]
      }
    ],
    "orderMisc": [
      {
        "id": 1,
        "quantity": 2,
        "orderId": 1,
        "miscId": 3
      },
      {
        "id": 2,
        "quantity": 1,
        "orderId": 1,
        "miscId": 1
      }
    ]
  },
  {
    "id": 2,
    "phone": "+7 977 777 7777",
    "userId": "uuid",
    "addressId": 1,
    "orderPizzas": [
      {
        "id": 2,
        "name": "пицца 1",
        "quantity": 1,
        "sauceId": 2,
        "doughId": 1,
        "sizeId": 1,
        "orderId": 2,
        "ingredients": [
          {
            "id": 3,
            "quantity": 2,
            "pizzaId": 2,
            "ingredientId": 2
          }
        ]
      },
      {
        "id": 3,
        "name": "пицца 2",
        "quantity": 1,
        "sauceId": 1,
        "doughId": 1,
        "sizeId": 2,
        "orderId": 2,
        "ingredients": [
          {
            "id": 4,
            "quantity": 1,
            "pizzaId": 3,
            "ingredientId": 2
          },
          {
            "id": 5,
            "quantity": 1,
            "pizzaId": 3,
            "ingredientId": 7
          },
          {
            "id": 6,
            "quantity": 1,
            "pizzaId": 3,
            "ingredientId": 12
          }
        ]
      }
    ],
    "orderAddress": {
      "id": 1,
      "name": "Первый",
      "street": "Ленина",
      "building": "5",
      "flat": "10",
      "comment": "",
      "userId": "uuid"
    }
  }
]